autodiff/__init__.py
autodiff/autodiff_.py
autodiff/elementary.py
autodiff/forward.py
autodiff/reverse.py
autodiff_djw-0.1.3.dist-info/LICENSE
autodiff_djw-0.1.3.dist-info/METADATA
autodiff_djw-0.1.3.dist-info/WHEEL
autodiff_djw-0.1.3.dist-info/top_level.txt
autodiff_djw-0.1.3.dist-info/RECORD
